{"web":{"client_id":"213623194290-r30b7fvhcuik07u7ll0qvetn8kph95u3.apps.googleusercontent.com","project_id":"ornate-entropy-175823","auth_uri":"https://accounts.google.com/o/oauth2/auth","token_uri":"https://accounts.google.com/o/oauth2/token","auth_provider_x509_cert_url":"https://www.googleapis.com/oauth2/v1/certs","client_secret":"-HPjKXSpn3sQ_v3Mr2qsnqlk","redirect_uris":["https://oram-portal-alicema15.c9users.io/","https://oram-portal-alicema15.c9users.io/clients","https://oram-portal-alicema15.c9users.io/clients/*"],"javascript_origins":["https://oram-portal-alicema15.c9users.io","http://oram-portal2.herokupapp.com","https://oram-portal2.herokuapp.com"]}}